mutwo/__init__.py
mutwo_third_party/__init__.py
mutwo_third_party/pydsm/__init__.py
mutwo_third_party/pydsm/pydsm/__init__.py
mutwo_third_party/pydsm/pydsm/iso226.py
mutwo-0.50.1.dist-info/LICENSE
mutwo-0.50.1.dist-info/METADATA
mutwo-0.50.1.dist-info/WHEEL
mutwo-0.50.1.dist-info/top_level.txt
mutwo-0.50.1.dist-info/RECORD
