Metadata-Version: 2.1
Name: mutwo
Version: 0.50.1
Summary: event based framework for generative art
Home-page: https://github.com/mutwo-org/mutwo
Author: Tim Pauli,  Levin Eric Zimmermann
Author-email: tim.pauli@folkwang-uni.de, levin.eric.zimmermann@posteo.eu
License: GPL
Project-URL: Documentation, https://mutwo.readthedocs.io/en/latest/
Platform: UNKNOWN
Requires-Python: >=3.9, <4
License-File: LICENSE
Provides-Extra: testing
Requires-Dist: nose ; extra == 'testing'
